chainalysis_data_solutions/__init__.py
chainalysis_data_solutions/constants.py
chainalysis_data_solutions/data_solutions_client.py
chainalysis_data_solutions/sql/__init__.py
chainalysis_data_solutions/sql/analytical.py
chainalysis_data_solutions/sql/sql.py
chainalysis_data_solutions/sql/transactional.py
chainalysis_data_solutions/util_functions/check_list_type.py
chainalysis_data_solutions/util_functions/exceptions.py
chainalysis_data_solutions/util_functions/requests.py
chainalysis_data_solutions/utils/__init__.py
chainalysis_data_solutions/utils/stringify.py
chainalysis_data_solutions/utils/utils.py
datasolutions-0.0.23.dist-info/METADATA
datasolutions-0.0.23.dist-info/WHEEL
datasolutions-0.0.23.dist-info/licenses/LICENCE
datasolutions-0.0.23.dist-info/RECORD
