Metadata-Version: 2.3
Name: DataSolutions
Version: 0.0.23
Summary: SDK functions for users to query Data Solutions databases.
Project-URL: Homepage, https://github.com/TransposeData/chainalysis-data-solutions-python-sdk
Author-email: "Rah Tarar (musa-tarar)" <musa.nishat@chainalysis.com>
License-File: LICENCE
Classifier: License :: OSI Approved :: MIT License
Classifier: Operating System :: OS Independent
Classifier: Programming Language :: Python :: 3
Requires-Python: >=3.8
